{
  "case_id": "case_fe37a2df9fca",
  "source": {
    "file_path": "政务治理/534785-数湖启智——多源异构_湖智算系统-项目策划书-f602ec7a.pdf",
    "file_name": "534785-数湖启智——多源异构_湖智算系统-项目策划书-f602ec7a.pdf",
    "category": "政务治理",
    "doc_type": "pdf",
    "parse_quality": "A",
    "include_in_kg": true,
    "education_level": "unknown",
    "year": "",
    "award_level": "",
    "school": ""
  },
  "document_stats": {
    "segment_count": 100,
    "full_text_chars": 58848,
    "core_text_chars": 4537,
    "appendix_start_index": 7,
    "has_appendix_evidence": true
  },
  "project_profile": {
    "project_name": "534785-数湖启智——多源异构_湖智算系统-项目策划书-f602ec7a",
    "target_users": [],
    "pain_points": [
      "第十九届“挑战杯”全国大学生课外学术科技作品竞赛“人工智能+”应用赛",
      "\"!!#!将数据作为新型生产要素，是我国的重大战略布局。充分发挥数据价值，抢占人工智能时代的先机十分重要。数据管理系统历经数据库、数据仓库的迭代升级，直至当前数据湖架构阶段。数据库和数据仓库擅长清洗、整理和结构化的数据，而数据湖是一个用于集中存储海量原始数据的“大仓库”。它不挑剔数据的类型和格式，也无需提前清洗整理或定义好严格的格式，就能低成本地容纳各种来源的庞大数据。 数据湖能够保存数据的原始状态和多样性， 再按需从湖中提取、加工并使用，提供了数据库和数据仓库难以比拟的灵活性。当前，国内外龙头企业纷纷投入数据湖建设，为人工智能产业搭建了数据基础设施。本项目分析了国内外主流的数据湖技术和系统，围绕政务数据的复杂性，分析了政务数据湖智能应用所面临的挑战，研发了多源异构数据湖智算系统，包含以下关键技术： （1）人机协作的数据提质：针对湖中数据多源异构，自身缺陷多，低成本通用清洗难的挑战，通过设计基于人工与机器的清洗融合方法，并对其进行细粒度的质量建模，通过人机协作，实现成本可控的高质量数据清洗融合，解决湖中原始数据的自身缺陷。 （2）任务感知的关系透视：针对数据湖中任务繁杂多样，数据难以精准适配的挑战，实现任务感知的精准数据发现，解决湖中数据与任务难以适配的挑战性问题，提升数据质量 （3）数据优选的模型提效：针对下游模型训练集规模庞大，参数训练慢的挑战，通过对全量训练数据与核心子集的梯度建模，实现具备理论保证的高质量核心子集选择与更新，降低数据分析的时间成本。 本项目负责人邓宇豪入学以来一直从事数据湖技术研究， 目前在CCF A类顶级会议发表论文6篇，主持国家自然科学基金，入选中国科协青年人才托举工程，团队成员共发表顶级会议和SCI论文10篇，受理发明专利1项。 通过合作推广，项目为国内多个城市提供了智慧公安、智慧医疗、智慧政务等服务，受到启元实验室主任廖湘科院士、科大讯飞副总裁王士进教授的高度赞扬。项目通过建立“数据湖建设” 、 “大数据医疗”等创新发展模式，推动了政府基础设施建设、高新企业创新业务发展，推动相关产业发展，加速了城市建设和经济发展，改善了人民生活水平。",
      "!\"#$%&'(%)*+&'%&',-%&'./%&'01",
      "目  录 234%5%%6 ............................................................................................................. 1 274%89:; ......................................................................................................... 2 2.1 项目背景 ......................................................................................................... 2 2.2 核心挑战 ......................................................................................................... 4 2.3 项目创新点 ..................................................................................................... 5 2<4%=>,-?@ABC ..................................................................................... 8 3.1 数据湖系统 ..................................................................................................... 8 3.2 数据清洗融合 ............................................................................................... 10 3.3数据发现 ........................................................................................................ 11 3.4数据分析 ........................................................................................................ 13 3.5 小结 ............................................................................................................... 14 2D4%EF@A?GH ........................................................................................... 16 4.1 核心技术1：人机协作的数据提质 .................................................................. 16 4.1.1数据清洗融合人机方法库构建 ................................................................ 16 4.1.2人在回路的方法质量建模 ......................................................................... 17 4.1.3成本质量感知的多方法协同 ..................................................................... 18 4.1.4实验验证 ..................................................................................................... 19 4.1.5 小结 ............................................................................................................ 22 4.2 核心技术2：任务感知的关系透视 ........................................................... 22 4.2.1语义感知的数据统一表征 ......................................................................... 23 4.2.2任务驱动的数据价值评估 ......................................................................... 25 4.2.3 API驱动的多任务封装 ............................................................................. 26 4.2.4 实验验证 .................................................................................................... 26 4.2.5 小结 ............................................................................................................ 32 4.3数据优选的模型提效 .................................................................................... 32 4.3.1核心特征选择的数据高效方法 ................................................................ 33 4.3.2 基于核心子集选择的数据高效方法 ....................................................... 34 4.3.3 动态环境下核心数据自适应更新 ........................................................... 35 4.3.4 实验验证 .................................................................................................... 36 4.3.5 小结 ............................................................................................................ 39"
    ],
    "solution": [
      "第十九届“挑战杯”全国大学生课外学术科技作品竞赛“人工智能+”应用赛",
      "\"!!#!将数据作为新型生产要素，是我国的重大战略布局。充分发挥数据价值，抢占人工智能时代的先机十分重要。数据管理系统历经数据库、数据仓库的迭代升级，直至当前数据湖架构阶段。数据库和数据仓库擅长清洗、整理和结构化的数据，而数据湖是一个用于集中存储海量原始数据的“大仓库”。它不挑剔数据的类型和格式，也无需提前清洗整理或定义好严格的格式，就能低成本地容纳各种来源的庞大数据。 数据湖能够保存数据的原始状态和多样性， 再按需从湖中提取、加工并使用，提供了数据库和数据仓库难以比拟的灵活性。当前，国内外龙头企业纷纷投入数据湖建设，为人工智能产业搭建了数据基础设施。本项目分析了国内外主流的数据湖技术和系统，围绕政务数据的复杂性，分析了政务数据湖智能应用所面临的挑战，研发了多源异构数据湖智算系统，包含以下关键技术： （1）人机协作的数据提质：针对湖中数据多源异构，自身缺陷多，低成本通用清洗难的挑战，通过设计基于人工与机器的清洗融合方法，并对其进行细粒度的质量建模，通过人机协作，实现成本可控的高质量数据清洗融合，解决湖中原始数据的自身缺陷。 （2）任务感知的关系透视：针对数据湖中任务繁杂多样，数据难以精准适配的挑战，实现任务感知的精准数据发现，解决湖中数据与任务难以适配的挑战性问题，提升数据质量 （3）数据优选的模型提效：针对下游模型训练集规模庞大，参数训练慢的挑战，通过对全量训练数据与核心子集的梯度建模，实现具备理论保证的高质量核心子集选择与更新，降低数据分析的时间成本。 本项目负责人邓宇豪入学以来一直从事数据湖技术研究， 目前在CCF A类顶级会议发表论文6篇，主持国家自然科学基金，入选中国科协青年人才托举工程，团队成员共发表顶级会议和SCI论文10篇，受理发明专利1项。 通过合作推广，项目为国内多个城市提供了智慧公安、智慧医疗、智慧政务等服务，受到启元实验室主任廖湘科院士、科大讯飞副总裁王士进教授的高度赞扬。项目通过建立“数据湖建设” 、 “大数据医疗”等创新发展模式，推动了政府基础设施建设、高新企业创新业务发展，推动相关产业发展，加速了城市建设和经济发展，改善了人民生活水平。",
      "!\"#$%&'(%)*+&'%&',-%&'./%&'01",
      "目  录 234%5%%6 ............................................................................................................. 1 274%89:; ......................................................................................................... 2 2.1 项目背景 ......................................................................................................... 2 2.2 核心挑战 ......................................................................................................... 4 2.3 项目创新点 ..................................................................................................... 5 2<4%=>,-?@ABC ..................................................................................... 8 3.1 数据湖系统 ..................................................................................................... 8 3.2 数据清洗融合 ............................................................................................... 10 3.3数据发现 ........................................................................................................ 11 3.4数据分析 ........................................................................................................ 13 3.5 小结 ............................................................................................................... 14 2D4%EF@A?GH ........................................................................................... 16 4.1 核心技术1：人机协作的数据提质 .................................................................. 16 4.1.1数据清洗融合人机方法库构建 ................................................................ 16 4.1.2人在回路的方法质量建模 ......................................................................... 17 4.1.3成本质量感知的多方法协同 ..................................................................... 18 4.1.4实验验证 ..................................................................................................... 19 4.1.5 小结 ............................................................................................................ 22 4.2 核心技术2：任务感知的关系透视 ........................................................... 22 4.2.1语义感知的数据统一表征 ......................................................................... 23 4.2.2任务驱动的数据价值评估 ......................................................................... 25 4.2.3 API驱动的多任务封装 ............................................................................. 26 4.2.4 实验验证 .................................................................................................... 26 4.2.5 小结 ............................................................................................................ 32 4.3数据优选的模型提效 .................................................................................... 32 4.3.1核心特征选择的数据高效方法 ................................................................ 33 4.3.2 基于核心子集选择的数据高效方法 ....................................................... 34 4.3.3 动态环境下核心数据自适应更新 ........................................................... 35 4.3.4 实验验证 .................................................................................................... 36 4.3.5 小结 ............................................................................................................ 39"
    ],
    "innovation_points": [
      "第十九届“挑战杯”全国大学生课外学术科技作品竞赛“人工智能+”应用赛",
      "\"!!#!将数据作为新型生产要素，是我国的重大战略布局。充分发挥数据价值，抢占人工智能时代的先机十分重要。数据管理系统历经数据库、数据仓库的迭代升级，直至当前数据湖架构阶段。数据库和数据仓库擅长清洗、整理和结构化的数据，而数据湖是一个用于集中存储海量原始数据的“大仓库”。它不挑剔数据的类型和格式，也无需提前清洗整理或定义好严格的格式，就能低成本地容纳各种来源的庞大数据。 数据湖能够保存数据的原始状态和多样性， 再按需从湖中提取、加工并使用，提供了数据库和数据仓库难以比拟的灵活性。当前，国内外龙头企业纷纷投入数据湖建设，为人工智能产业搭建了数据基础设施。本项目分析了国内外主流的数据湖技术和系统，围绕政务数据的复杂性，分析了政务数据湖智能应用所面临的挑战，研发了多源异构数据湖智算系统，包含以下关键技术： （1）人机协作的数据提质：针对湖中数据多源异构，自身缺陷多，低成本通用清洗难的挑战，通过设计基于人工与机器的清洗融合方法，并对其进行细粒度的质量建模，通过人机协作，实现成本可控的高质量数据清洗融合，解决湖中原始数据的自身缺陷。 （2）任务感知的关系透视：针对数据湖中任务繁杂多样，数据难以精准适配的挑战，实现任务感知的精准数据发现，解决湖中数据与任务难以适配的挑战性问题，提升数据质量 （3）数据优选的模型提效：针对下游模型训练集规模庞大，参数训练慢的挑战，通过对全量训练数据与核心子集的梯度建模，实现具备理论保证的高质量核心子集选择与更新，降低数据分析的时间成本。 本项目负责人邓宇豪入学以来一直从事数据湖技术研究， 目前在CCF A类顶级会议发表论文6篇，主持国家自然科学基金，入选中国科协青年人才托举工程，团队成员共发表顶级会议和SCI论文10篇，受理发明专利1项。 通过合作推广，项目为国内多个城市提供了智慧公安、智慧医疗、智慧政务等服务，受到启元实验室主任廖湘科院士、科大讯飞副总裁王士进教授的高度赞扬。项目通过建立“数据湖建设” 、 “大数据医疗”等创新发展模式，推动了政府基础设施建设、高新企业创新业务发展，推动相关产业发展，加速了城市建设和经济发展，改善了人民生活水平。",
      "!\"#$%&'(%)*+&'%&',-%&'./%&'01",
      "目  录 234%5%%6 ............................................................................................................. 1 274%89:; ......................................................................................................... 2 2.1 项目背景 ......................................................................................................... 2 2.2 核心挑战 ......................................................................................................... 4 2.3 项目创新点 ..................................................................................................... 5 2<4%=>,-?@ABC ..................................................................................... 8 3.1 数据湖系统 ..................................................................................................... 8 3.2 数据清洗融合 ............................................................................................... 10 3.3数据发现 ........................................................................................................ 11 3.4数据分析 ........................................................................................................ 13 3.5 小结 ............................................................................................................... 14 2D4%EF@A?GH ........................................................................................... 16 4.1 核心技术1：人机协作的数据提质 .................................................................. 16 4.1.1数据清洗融合人机方法库构建 ................................................................ 16 4.1.2人在回路的方法质量建模 ......................................................................... 17 4.1.3成本质量感知的多方法协同 ..................................................................... 18 4.1.4实验验证 ..................................................................................................... 19 4.1.5 小结 ............................................................................................................ 22 4.2 核心技术2：任务感知的关系透视 ........................................................... 22 4.2.1语义感知的数据统一表征 ......................................................................... 23 4.2.2任务驱动的数据价值评估 ......................................................................... 25 4.2.3 API驱动的多任务封装 ............................................................................. 26 4.2.4 实验验证 .................................................................................................... 26 4.2.5 小结 ............................................................................................................ 32 4.3数据优选的模型提效 .................................................................................... 32 4.3.1核心特征选择的数据高效方法 ................................................................ 33 4.3.2 基于核心子集选择的数据高效方法 ....................................................... 34 4.3.3 动态环境下核心数据自适应更新 ........................................................... 35 4.3.4 实验验证 .................................................................................................... 36 4.3.5 小结 ............................................................................................................ 39"
    ],
    "business_model": [],
    "market_analysis": [],
    "execution_plan": [
      "第十九届“挑战杯”全国大学生课外学术科技作品竞赛“人工智能+”应用赛",
      "第⼗九届挑战杯全国⼤学⽣课外学术科技作品竞赛 ⼈⼯智能+专项赛",
      "项目计划书 !    !\"#$%&&'()*++,-./'0(*123&&&!!45678%&&&&&&&&&&&&&9:;&&&&&&&&&&&&&&&&&!!<=>?%&&&@ABCADECFGHCIJK&&&&&&&&&&IJKCLMCN:OCPQRCSTU&&&&&!!",
      "\"!!#!将数据作为新型生产要素，是我国的重大战略布局。充分发挥数据价值，抢占人工智能时代的先机十分重要。数据管理系统历经数据库、数据仓库的迭代升级，直至当前数据湖架构阶段。数据库和数据仓库擅长清洗、整理和结构化的数据，而数据湖是一个用于集中存储海量原始数据的“大仓库”。它不挑剔数据的类型和格式，也无需提前清洗整理或定义好严格的格式，就能低成本地容纳各种来源的庞大数据。 数据湖能够保存数据的原始状态和多样性， 再按需从湖中提取、加工并使用，提供了数据库和数据仓库难以比拟的灵活性。当前，国内外龙头企业纷纷投入数据湖建设，为人工智能产业搭建了数据基础设施。本项目分析了国内外主流的数据湖技术和系统，围绕政务数据的复杂性，分析了政务数据湖智能应用所面临的挑战，研发了多源异构数据湖智算系统，包含以下关键技术： （1）人机协作的数据提质：针对湖中数据多源异构，自身缺陷多，低成本通用清洗难的挑战，通过设计基于人工与机器的清洗融合方法，并对其进行细粒度的质量建模，通过人机协作，实现成本可控的高质量数据清洗融合，解决湖中原始数据的自身缺陷。 （2）任务感知的关系透视：针对数据湖中任务繁杂多样，数据难以精准适配的挑战，实现任务感知的精准数据发现，解决湖中数据与任务难以适配的挑战性问题，提升数据质量 （3）数据优选的模型提效：针对下游模型训练集规模庞大，参数训练慢的挑战，通过对全量训练数据与核心子集的梯度建模，实现具备理论保证的高质量核心子集选择与更新，降低数据分析的时间成本。 本项目负责人邓宇豪入学以来一直从事数据湖技术研究， 目前在CCF A类顶级会议发表论文6篇，主持国家自然科学基金，入选中国科协青年人才托举工程，团队成员共发表顶级会议和SCI论文10篇，受理发明专利1项。 通过合作推广，项目为国内多个城市提供了智慧公安、智慧医疗、智慧政务等服务，受到启元实验室主任廖湘科院士、科大讯飞副总裁王士进教授的高度赞扬。项目通过建立“数据湖建设” 、 “大数据医疗”等创新发展模式，推动了政府基础设施建设、高新企业创新业务发展，推动相关产业发展，加速了城市建设和经济发展，改善了人民生活水平。",
      "!\"#$%&'(%)*+&'%&',-%&'./%&'01",
      "目  录 234%5%%6 ............................................................................................................. 1 274%89:; ......................................................................................................... 2 2.1 项目背景 ......................................................................................................... 2 2.2 核心挑战 ......................................................................................................... 4 2.3 项目创新点 ..................................................................................................... 5 2<4%=>,-?@ABC ..................................................................................... 8 3.1 数据湖系统 ..................................................................................................... 8 3.2 数据清洗融合 ............................................................................................... 10 3.3数据发现 ........................................................................................................ 11 3.4数据分析 ........................................................................................................ 13 3.5 小结 ............................................................................................................... 14 2D4%EF@A?GH ........................................................................................... 16 4.1 核心技术1：人机协作的数据提质 .................................................................. 16 4.1.1数据清洗融合人机方法库构建 ................................................................ 16 4.1.2人在回路的方法质量建模 ......................................................................... 17 4.1.3成本质量感知的多方法协同 ..................................................................... 18 4.1.4实验验证 ..................................................................................................... 19 4.1.5 小结 ............................................................................................................ 22 4.2 核心技术2：任务感知的关系透视 ........................................................... 22 4.2.1语义感知的数据统一表征 ......................................................................... 23 4.2.2任务驱动的数据价值评估 ......................................................................... 25 4.2.3 API驱动的多任务封装 ............................................................................. 26 4.2.4 实验验证 .................................................................................................... 26 4.2.5 小结 ............................................................................................................ 32 4.3数据优选的模型提效 .................................................................................... 32 4.3.1核心特征选择的数据高效方法 ................................................................ 33 4.3.2 基于核心子集选择的数据高效方法 ....................................................... 34 4.3.3 动态环境下核心数据自适应更新 ........................................................... 35 4.3.4 实验验证 .................................................................................................... 36 4.3.5 小结 ............................................................................................................ 39"
    ],
    "risk_control": []
  },
  "risk_flags": [
    "weak_user_evidence",
    "compliance_not_covered"
  ],
  "summary": "第十九届“挑战杯”全国大学生课外学术科技作品竞赛“人工智能+”应用赛 第⼗九届挑战杯全国⼤学⽣课外学术科技作品竞赛 ⼈⼯智能+专项赛 项目计划书 ! !\"#$%&&'()*++,-./'0(*123&&&!!45678%&&&&&&&&&&&&&9:;&&&&&&&&&&&&&&&&&!!<=>?%&&&@ABCADECFGHCIJK&&&&&&&&&&IJKCLMCN:OCPQRCSTU&&&&&!! 第十九届“挑战杯”全国大学生课外学术科技作品竞赛“人工智能+”应用赛 第十九届“挑战杯”全国大学生课外学术科技作品竞赛“人工智能+”应用赛 第十九届“挑战杯”全国大学生课外学术科技作品竞赛“人工智能+”应用赛 第十九届“挑战杯”全国大学生课外学术科技作品竞赛“人工智能+”应用赛 \"!!#!将数据作为新型生产要素，是我国的重大战略布局。充分发挥数据价值，抢占人工智能时代的先机十分重要。数据管理系统历经数据库、数据仓库的迭代升级，直至当前数据湖架构阶段。数据库和数据仓库擅长清洗、整理和结构化的数据，而数据湖是一个用于集中存储海量原始数据的“大仓库”。它不挑剔数据的类型和格式，也无需提前清洗",
  "confidence": 0.9,
  "generated_at": "2026-03-07T07:02:21Z"
}